<?xml version="1.0" encoding="UTF-8"?>
<!DOCTYPE mapper PUBLIC "-//mybatis.org//DTD Mapper 3.0//EN" "http://mybatis.org/dtd/mybatis-3-mapper.dtd">
<mapper namespace="site.gaoyisheng.dao.QuestionMapper">
  <resultMap id="BaseResultMap" type="site.gaoyisheng.pojo.Question">
    <!--
      WARNING - @mbg.generated
      This element is automatically generated by MyBatis Generator, do not modify.
    -->
    <id column="id" jdbcType="INTEGER" property="id" />
    <result column="name" jdbcType="VARCHAR" property="name" />
    <result column="team_id" jdbcType="INTEGER" property="teamId" />
    <result column="detail" jdbcType="VARCHAR" property="detail" />
    <result column="deadtime" jdbcType="TIMESTAMP" property="deadtime" />
    <result column="diffculty" jdbcType="REAL" property="diffculty" />
    <result column="result" jdbcType="CHAR" property="result" />
    <result column="answercode" jdbcType="VARCHAR" property="answercode" />
    <result column="answerdetail" jdbcType="VARCHAR" property="answerdetail" />
  </resultMap>
  <sql id="Base_Column_List">
    <!--
      WARNING - @mbg.generated
      This element is automatically generated by MyBatis Generator, do not modify.
    -->
    id, name, team_id, detail, deadtime, diffculty, result, answercode, answerdetail
  </sql>
  <select id="selectByPrimaryKey" parameterType="java.lang.Integer" resultMap="BaseResultMap">
    <!--
      WARNING - @mbg.generated
      This element is automatically generated by MyBatis Generator, do not modify.
    -->
    select 
    <include refid="Base_Column_List" />
    from public."question"
    where id = #{id,jdbcType=INTEGER}
  </select>
  <delete id="deleteByPrimaryKey" parameterType="java.lang.Integer">
    <!--
      WARNING - @mbg.generated
      This element is automatically generated by MyBatis Generator, do not modify.
    -->
    delete from public."question"
    where id = #{id,jdbcType=INTEGER}
  </delete>
  <insert id="insert" parameterType="site.gaoyisheng.pojo.Question">
    <!--
      WARNING - @mbg.generated
      This element is automatically generated by MyBatis Generator, do not modify.
    -->
    insert into public."question" (id, name, team_id, 
      detail, deadtime, diffculty, 
      result, answercode, answerdetail
      )
    values (#{id,jdbcType=INTEGER}, #{name,jdbcType=VARCHAR}, #{teamId,jdbcType=INTEGER}, 
      #{detail,jdbcType=VARCHAR}, #{deadtime,jdbcType=TIMESTAMP}, #{diffculty,jdbcType=REAL}, 
      #{result,jdbcType=CHAR}, #{answercode,jdbcType=VARCHAR}, #{answerdetail,jdbcType=VARCHAR}
      )
  </insert>
  <insert id="insertSelective" parameterType="site.gaoyisheng.pojo.Question">
    <!--
      WARNING - @mbg.generated
      This element is automatically generated by MyBatis Generator, do not modify.
    -->
    insert into public."question"
    <trim prefix="(" suffix=")" suffixOverrides=",">
      <if test="id != null">
        id,
      </if>
      <if test="name != null">
        name,
      </if>
      <if test="teamId != null">
        team_id,
      </if>
      <if test="detail != null">
        detail,
      </if>
      <if test="deadtime != null">
        deadtime,
      </if>
      <if test="diffculty != null">
        diffculty,
      </if>
      <if test="result != null">
        result,
      </if>
      <if test="answercode != null">
        answercode,
      </if>
      <if test="answerdetail != null">
        answerdetail,
      </if>
    </trim>
    <trim prefix="values (" suffix=")" suffixOverrides=",">
      <if test="id != null">
        #{id,jdbcType=INTEGER},
      </if>
      <if test="name != null">
        #{name,jdbcType=VARCHAR},
      </if>
      <if test="teamId != null">
        #{teamId,jdbcType=INTEGER},
      </if>
      <if test="detail != null">
        #{detail,jdbcType=VARCHAR},
      </if>
      <if test="deadtime != null">
        #{deadtime,jdbcType=TIMESTAMP},
      </if>
      <if test="diffculty != null">
        #{diffculty,jdbcType=REAL},
      </if>
      <if test="result != null">
        #{result,jdbcType=CHAR},
      </if>
      <if test="answercode != null">
        #{answercode,jdbcType=VARCHAR},
      </if>
      <if test="answerdetail != null">
        #{answerdetail,jdbcType=VARCHAR},
      </if>
    </trim>
  </insert>
  <update id="updateByPrimaryKeySelective" parameterType="site.gaoyisheng.pojo.Question">
    <!--
      WARNING - @mbg.generated
      This element is automatically generated by MyBatis Generator, do not modify.
    -->
    update public."question"
    <set>
      <if test="name != null">
        name = #{name,jdbcType=VARCHAR},
      </if>
      <if test="teamId != null">
        team_id = #{teamId,jdbcType=INTEGER},
      </if>
      <if test="detail != null">
        detail = #{detail,jdbcType=VARCHAR},
      </if>
      <if test="deadtime != null">
        deadtime = #{deadtime,jdbcType=TIMESTAMP},
      </if>
      <if test="diffculty != null">
        diffculty = #{diffculty,jdbcType=REAL},
      </if>
      <if test="result != null">
        result = #{result,jdbcType=CHAR},
      </if>
      <if test="answercode != null">
        answercode = #{answercode,jdbcType=VARCHAR},
      </if>
      <if test="answerdetail != null">
        answerdetail = #{answerdetail,jdbcType=VARCHAR},
      </if>
    </set>
    where id = #{id,jdbcType=INTEGER}
  </update>
  <update id="updateByPrimaryKey" parameterType="site.gaoyisheng.pojo.Question">
    <!--
      WARNING - @mbg.generated
      This element is automatically generated by MyBatis Generator, do not modify.
    -->
    update public."question"
    set name = #{name,jdbcType=VARCHAR},
      team_id = #{teamId,jdbcType=INTEGER},
      detail = #{detail,jdbcType=VARCHAR},
      deadtime = #{deadtime,jdbcType=TIMESTAMP},
      diffculty = #{diffculty,jdbcType=REAL},
      result = #{result,jdbcType=CHAR},
      answercode = #{answercode,jdbcType=VARCHAR},
      answerdetail = #{answerdetail,jdbcType=VARCHAR}
    where id = #{id,jdbcType=INTEGER}
  </update>
</mapper>